selectio/__init__.py
selectio/selectio.py
selectio/simdata.py
selectio/tests.py
selectio/utils.py
selectio/models/__init__.py
selectio/models/blr.py
selectio/models/mi.py
selectio/models/rdt.py
selectio/models/rf.py
selectio/models/spearman.py
selectio/models/xicor.py
selectio/settings/__init__.py
selectio/settings/settings_featureimportance.yaml
selectio-0.1.7.dist-info/LICENSE
selectio-0.1.7.dist-info/METADATA
selectio-0.1.7.dist-info/WHEEL
selectio-0.1.7.dist-info/top_level.txt
selectio-0.1.7.dist-info/RECORD
