Metadata-Version: 2.1
Name: selectio
Version: 0.1.7
Summary: Multi-model Feature Importance Scoring and Auto Feature Selection
Home-page: https://github.com/sebhaan/selectio
Author: Sebastian Haan
License: MIT
Classifier: Programming Language :: Python :: 3
Classifier: Operating System :: OS Independent
Requires-Python: >=3.8
License-File: LICENSE
Requires-Dist: scikit-learn (>=1.0)
Requires-Dist: numpy (>=1.21)
Requires-Dist: pandas (>=1.3.5)
Requires-Dist: pyyaml (>=6.0)
Requires-Dist: scipy (>=1.7.3)
Requires-Dist: matplotlib (>=3.5)
